ajent/__init__.py
ajent/llm_client.py
ajent/llm_factory.py
ajent/response_serializer.py
ajent/openai/__init__.py
ajent/openai/openai_client.py
ajent-0.4.0.dist-info/LICENSE
ajent-0.4.0.dist-info/METADATA
ajent-0.4.0.dist-info/WHEEL
ajent-0.4.0.dist-info/top_level.txt
ajent-0.4.0.dist-info/RECORD
