Metadata-Version: 2.1
Name: ajent
Version: 0.4.0
Summary: Library to implement your own Ajent Server API
Author: Gustavo Barros
Author-email: gbarrospe@gmail.com
License-File: LICENSE
Requires-Dist: openai
